L9/__init__.py
L9/l9_func.py
L9-0.0.6.dist-info/METADATA
L9-0.0.6.dist-info/WHEEL
L9-0.0.6.dist-info/top_level.txt
L9-0.0.6.dist-info/RECORD
